langchain_asimov/__init__.py
langchain_asimov/_version.py
langchain_asimov/document_loaders.py
langchain_asimov/errors.py
langchain_asimov/py.typed
langchain_asimov-0.0.2.dist-info/METADATA
langchain_asimov-0.0.2.dist-info/WHEEL
langchain_asimov-0.0.2.dist-info/licenses/UNLICENSE
langchain_asimov-0.0.2.dist-info/RECORD
