Metadata-Version: 2.4
Name: langchain-asimov
Version: 0.0.2
Summary: LangChain integration with the ASIMOV platform.
Project-URL: Homepage, https://github.com/asimov-platform
Project-URL: Repository, https://github.com/asimov-platform/langchain-asimov
Project-URL: Changelog, https://github.com/asimov-platform/langchain-asimov/blob/master/CHANGES.md
Project-URL: Releases, https://github.com/asimov-platform/langchain-asimov/releases
Project-URL: Issues, https://github.com/asimov-platform/langchain-asimov/issues
Author-email: ASIMOV Protocol <support@asimov.so>
License-Expression: Unlicense
License-File: UNLICENSE
Requires-Python: >=3.9
Requires-Dist: langchain-core>=0.3
Requires-Dist: pyld>=2
